bakit/__init__.py
bakit/cli.py
bakit/config.py
bakit/init.py
bakit/settings.py
bakit/shell.py
bakit/arq/__init__.py
bakit/arq/decorators.py
bakit/arq/task_loader.py
bakit/arq/worker.py
bakit/sanic/__init__.py
bakit/sanic/app.py
bakit/sanic/decorators.py
bakit/sanic/listeners.py
bakit/sanic/middlewares.py
bakit/sanic/views.py
bakit/sanic/static/favicon.ico
bakit/sanic/static/favicon.png
bakit/utils/__init__.py
bakit/utils/db.py
bakit/utils/discord.py
bakit/utils/metrics.py
bakit/utils/sql_helpers.py
balabs_kit-0.0.8.dist-info/METADATA
balabs_kit-0.0.8.dist-info/WHEEL
balabs_kit-0.0.8.dist-info/RECORD
