Metadata-Version: 2.4
Name: balabs-kit
Version: 0.0.8
Author-email: tsifrer <3967564+tsifrer@users.noreply.github.com>
License-Expression: Apache-2.0
Requires-Python: >=3.13
Requires-Dist: aiocache[redis]>=0.12.3
Requires-Dist: aiohttp>=3.13.3
Requires-Dist: asyncclick>=8.3.0.7
Requires-Dist: asyncpg>=0.31.0
Requires-Dist: discord-py>=2.6.4
Requires-Dist: environs>=14.5.0
Requires-Dist: ipython>=9.8.0
Requires-Dist: nest-asyncio>=1.6.0
Requires-Dist: sentry-sdk>=2.48.0
Requires-Dist: statsd>=4.0.1
Requires-Dist: tortoise-orm>=0.25.1
Requires-Dist: uvloop>=0.22.1
Provides-Extra: arq
Requires-Dist: arq<1.0.0,>=0.26.3; extra == 'arq'
Requires-Dist: tortoise-plastron>=0.1.1; extra == 'arq'
Provides-Extra: sanic
Requires-Dist: orjson>=3.11.5; extra == 'sanic'
Requires-Dist: sanic-ext>=24.12.0; extra == 'sanic'
Requires-Dist: sanic>=25.3.0; extra == 'sanic'
